fileunity/__init__.py
fileunity/_basics.py
fileunity-1.3.1.dist-info/LICENSE.txt
fileunity-1.3.1.dist-info/METADATA
fileunity-1.3.1.dist-info/WHEEL
fileunity-1.3.1.dist-info/top_level.txt
fileunity-1.3.1.dist-info/RECORD
