Metadata-Version: 2.1
Name: fileunity
Version: 1.3.1
Summary: easy data objects to load and save
Author-email: Johannes <johannes-programming@posteo.org>
License: The MIT License (MIT)
Project-URL: Source, https://github.com/johannes-programming/fileunity
Project-URL: Download, https://pypi.org/project/fileunity/#files
Classifier: License :: OSI Approved :: MIT License
Classifier: Programming Language :: Python
Classifier: Programming Language :: Python :: 3
Requires-Python: >=3.11
License-File: LICENSE.txt
Requires-Dist: pandas >=2.1.2
Requires-Dist: simple-tsv >=1.0
Requires-Dist: tomli-w >=1.0
